README.md
setup.py
lbrlabs_pulumi_aws_controltower/__init__.py
lbrlabs_pulumi_aws_controltower/_inputs.py
lbrlabs_pulumi_aws_controltower/_utilities.py
lbrlabs_pulumi_aws_controltower/control_tower_aws_account.py
lbrlabs_pulumi_aws_controltower/outputs.py
lbrlabs_pulumi_aws_controltower/provider.py
lbrlabs_pulumi_aws_controltower/pulumi-plugin.json
lbrlabs_pulumi_aws_controltower/py.typed
lbrlabs_pulumi_aws_controltower.egg-info/PKG-INFO
lbrlabs_pulumi_aws_controltower.egg-info/SOURCES.txt
lbrlabs_pulumi_aws_controltower.egg-info/dependency_links.txt
lbrlabs_pulumi_aws_controltower.egg-info/not-zip-safe
lbrlabs_pulumi_aws_controltower.egg-info/requires.txt
lbrlabs_pulumi_aws_controltower.egg-info/top_level.txt
lbrlabs_pulumi_aws_controltower/config/__init__.py
lbrlabs_pulumi_aws_controltower/config/outputs.py
lbrlabs_pulumi_aws_controltower/config/vars.py