Metadata-Version: 2.1
Name: lbrlabs-pulumi-aws-controltower
Version: 0.0.2
Summary: A Pulumi package for creating and managing control tower accounts.
Home-page: https://leebriggs.co.uk/projects#pulumi-awscontroltower
License: Apache-2.0
Project-URL: Repository, https://github.com/lbrlabs/pulumi-awscontroltower
Keywords: pulumi aws controltower lbrlabs
Platform: UNKNOWN
Requires-Python: >=3.7
